freedan/__init__.py
freedan-1.0.dist-info/METADATA
freedan-1.0.dist-info/WHEEL
freedan-1.0.dist-info/top_level.txt
freedan-1.0.dist-info/RECORD
