Metadata-Version: 2.1
Name: freedan
Version: 1.0
Summary: Coming soon
Author: Nitesh Gupta
